hou_flask_psycopg2/__init__.py
hou_flask_psycopg2/exceptions.py
hou_flask_psycopg2/flask.py
hou_flask_psycopg2/py.typed
hou_flask_psycopg2/test_utils.py
hou_flask_psycopg2/utils.py
hou_flask_psycopg2-0.0.7.dist-info/METADATA
hou_flask_psycopg2-0.0.7.dist-info/WHEEL
hou_flask_psycopg2-0.0.7.dist-info/top_level.txt
hou_flask_psycopg2-0.0.7.dist-info/RECORD
