Metadata-Version: 2.1
Name: hou-flask-psycopg2
Version: 0.0.7
Summary: Highly Opinionated Utils: Flask Psycopg2
Home-page: https://github.com/timmartin19/hou-flask-psycopg2
Author: Tim Martin
Author-email: oss@timmartin.me
License: UNKNOWN
Keywords: oss_auth
Platform: UNKNOWN
Classifier: Development Status :: 2 - Pre-Alpha
Classifier: Intended Audience :: Developers
Classifier: Natural Language :: English
Classifier: Programming Language :: Python :: 3
Classifier: Programming Language :: Python :: 3.5
Classifier: Programming Language :: Python :: 3.6
Classifier: Programming Language :: Python :: 3.7
Requires-Dist: psycopg2
Requires-Dist: python-rapidjson
Requires-Dist: flask
Requires-Dist: werkzeug
